psychopykit/__init__.py
psychopykit/et2bids.py
psychopykit/eyetracking.py
psychopykit/log2bids.py
psychopykit-2023.8.17.dist-info/LICENSE
psychopykit-2023.8.17.dist-info/METADATA
psychopykit-2023.8.17.dist-info/WHEEL
psychopykit-2023.8.17.dist-info/entry_points.txt
psychopykit-2023.8.17.dist-info/top_level.txt
psychopykit-2023.8.17.dist-info/RECORD
