Metadata-Version: 2.1
Name: psychopykit
Version: 2023.8.17
Summary: Psychopy output conversion utilities
Home-page: https://github.com/adolphslab/psychopykit
Author: Mike Tyszka
Author-email: jmt@caltech.edu
Project-URL: Bug Reports, https://github.com/adolphslab/psychopykit/issues
Project-URL: Funding, http://conte.caltech.edu/
Project-URL: Source, https://github.com/adolphslab/psychopykit/
Keywords: neuroimaging MRI fMRI DICOM BIDS
Classifier: Development Status :: 4 - Beta
Classifier: Intended Audience :: Science/Research
Classifier: Topic :: Scientific/Engineering
Classifier: License :: OSI Approved :: MIT License
Classifier: Programming Language :: Python :: 3.9
Classifier: Programming Language :: Python :: 3.10
Requires-Python: >=3.9, <4
License-File: LICENSE
